adoc/__init__.py
adoc/__main__.py
adoc/cli.py
adoc/codegen.py
adoc/errors.py
adoc/httpd.py
adoc/models.py
adoc/parser.py
adoc/utils.py
adoc/version.py
adoc/writer.py
adoc/formats/__init__.py
adoc/formats/md.py
adoc/formats/rst.py
adoc/templates/css-adoc.mako
adoc/templates/css-normalize.mako
adoc/templates/css-print.mako
adoc/templates/css-pygments.mako
adoc/templates/css-rst.mako
adoc/templates/html.mako
adoc/templates/macros.mako
adoc-0.1.5.dist-info/LICENSE.txt
adoc-0.1.5.dist-info/METADATA
adoc-0.1.5.dist-info/RECORD
adoc-0.1.5.dist-info/WHEEL
adoc-0.1.5.dist-info/entry_points.txt
adoc-0.1.5.dist-info/top_level.txt
