Metadata-Version: 2.1
Name: adoc
Version: 0.1.5
Summary: Python code documentation generator
Home-page: https://github.com/saalaa/adoc
Author: Benoit Myard
Author-email: benoit@myard.xyz
License: BSD
Project-URL: Documentation, https://saalaa.github.io/adoc
Project-URL: Issues, https://github.com/saalaa/adoc/issues
Platform: UNKNOWN
Classifier: Development Status :: 3 - Alpha
Classifier: Environment :: Web Environment
Classifier: Intended Audience :: Developers
Classifier: Intended Audience :: Education
Classifier: Intended Audience :: Information Technology
Classifier: Intended Audience :: Science/Research
Classifier: Intended Audience :: System Administrators
Classifier: License :: OSI Approved :: BSD License
Classifier: Operating System :: MacOS :: MacOS X
Classifier: Operating System :: Microsoft :: Windows
Classifier: Operating System :: OS Independent
Classifier: Operating System :: POSIX :: BSD
Classifier: Operating System :: POSIX :: Linux
Classifier: Operating System :: POSIX
Classifier: Operating System :: Unix
Classifier: Programming Language :: Python :: 3
Classifier: Programming Language :: Python :: 3.5
Classifier: Programming Language :: Python :: 3.6
Classifier: Programming Language :: Python
Classifier: Topic :: Internet :: WWW/HTTP :: Dynamic Content
Requires-Python: ~=3.5
Requires-Dist: beautifulsoup4 (==4.6.0)
Requires-Dist: bs4 (==0.0.1)
Requires-Dist: docutils (==0.14)
Requires-Dist: Mako (==1.0.7)
Requires-Dist: Markdown (==2.6.11)
Requires-Dist: MarkupSafe (==1.0)
Requires-Dist: Pygments (==2.2.0)
Requires-Dist: colorlog (==3.1.4)
